loosenesspgmdata/__init__.py
loosenesspgmdata/looseness.py
loosenesspgmdata-0.0.1.dist-info/METADATA
loosenesspgmdata-0.0.1.dist-info/WHEEL
loosenesspgmdata-0.0.1.dist-info/top_level.txt
loosenesspgmdata-0.0.1.dist-info/RECORD
