Metadata-Version: 2.1
Name: loosenesspgmdata
Version: 0.0.1
Summary: My first Python package
Author: Supriya
Author-email: <supriyasuhas058@email.com>
Keywords: python,first package
Requires-Dist: pandas
Requires-Dist: numpy
Requires-Dist: matplotlib
Requires-Dist: paho-mqtt
Requires-Dist: scipy
Requires-Dist: scikit-learn
